storelet
