Metadata-Version: 1.1
Name: storelet
Version: 0.1.5
Summary: Simple and easy framework for writing backup scripts
Home-page: http://github.com/markembling/storelet
Author: Mark Embling
Author-email: mark@markembling.info
License: BSD
Platform: UNKNOWN
Classifier: Development Status :: 3 - Alpha
Classifier: Intended Audience :: Developers
Classifier: Intended Audience :: System Administrators
Classifier: License :: OSI Approved :: BSD License
Classifier: Topic :: System :: Archiving :: Backup
